Metadata-Version: 1.1
Name: BESST
Version: 2.2.8
Summary: Scaffolder for genomic assemblies.
Home-page: https://github.com/ksahlin/BESST
Author: Kristoffer Sahlin
Author-email: kristoffer.sahlin@scilifelab.se
License: GPLv3
Platform: UNKNOWN
Classifier: Development Status :: 4 - Beta
Classifier: Environment :: Console
Classifier: Intended Audience :: Science/Research
Classifier: Natural Language :: English
Classifier: Operating System :: POSIX :: Linux
Classifier: Programming Language :: Python
Classifier: Topic :: Scientific/Engineering :: Bio-Informatics
